saea_benchmark/__init__.py
saea_benchmark/align_seqs.py
saea_benchmark/experiment.py
saea_benchmark/model_eval.py
saea_benchmark/plotting/benchmark.py
saea_benchmark/plotting/eda.py
saea_benchmark-0.1.11.dist-info/licenses/LICENSE
saea_benchmark-0.1.11.dist-info/WHEEL
saea_benchmark-0.1.11.dist-info/METADATA
saea_benchmark-0.1.11.dist-info/RECORD
