Metadata-Version: 2.4
Name: saea_benchmark
Version: 0.1.11
Summary: A package for benchmarking biological data spliting methods
Author-email: Qianyu Zheng <zhengqianyu0227@gmail.com>
Requires-Python: >=3.9
Classifier: Programming Language :: Python :: 3
Classifier: Operating System :: OS Independent
License-File: LICENSE
Requires-Dist: pyparsing
Requires-Dist: pandas
Requires-Dist: numpy
Requires-Dist: scikit-learn
Requires-Dist: tqdm
Requires-Dist: optuna
Requires-Dist: scanpy
Requires-Dist: matplotlib
Requires-Dist: ruff
Requires-Dist: pre-commit
Project-URL: Homepage, https://github.com/qzheng75/saea_benchmark
Project-URL: Repository, https://github.com/qzheng75/saea_benchmark
